mediakit/__init__.py
mediakit/constants.py
mediakit/exceptions.py
mediakit/globals.py
mediakit/info.py
mediakit/main.py
mediakit/actions/__init__.py
mediakit/actions/download.py
mediakit/actions/download_from_playlist.py
mediakit/actions/main.py
mediakit/cli/__init__.py
mediakit/cli/arguments.py
mediakit/cli/colors.py
mediakit/cli/loadble_cli.py
mediakit/cli/loadble_cli_store.py
mediakit/cli/screen.py
mediakit/cli/download/__init__.py
mediakit/cli/download/download_cli.py
mediakit/cli/download/download_cli_formatter.py
mediakit/cli/download/download_cli_store.py
mediakit/media/__init__.py
mediakit/media/convert.py
mediakit/media/download.py
mediakit/utils/__init__.py
mediakit/utils/commands.py
mediakit/utils/ffmpeg.py
mediakit/utils/files.py
mediakit/utils/format.py
mediakit/utils/lists.py
mediakit/utils/regex.py
mediakit-0.7.2.dist-info/LICENSE
mediakit-0.7.2.dist-info/METADATA
mediakit-0.7.2.dist-info/WHEEL
mediakit-0.7.2.dist-info/entry_points.txt
mediakit-0.7.2.dist-info/top_level.txt
mediakit-0.7.2.dist-info/RECORD
