Metadata-Version: 2.1
Name: mediakit
Version: 0.7.2
Summary: Download YouTube videos fast, directly from the command line
Home-page: https://github.com/diego-aquino/mediakit
Author: Diego Aquino
Author-email: diegocruzdeaquino@gmail.com
License: GPL-3.0
Download-URL: https://github.com/diego-aquino/mediakit/archive/v0.7.2.tar.gz
Keywords: youtube,media,video,audio,download,convert,command line,cli
Platform: UNKNOWN
Classifier: Development Status :: 4 - Beta
Classifier: Environment :: Console
Classifier: Intended Audience :: End Users/Desktop
Classifier: License :: OSI Approved :: GNU General Public License v3 (GPLv3)
Classifier: Natural Language :: English
Classifier: Operating System :: Unix
Classifier: Programming Language :: Python :: 3.6
Classifier: Programming Language :: Python :: 3.7
Classifier: Programming Language :: Python :: 3.8
Classifier: Programming Language :: Python :: 3.9
Classifier: Topic :: Multimedia :: Video
Classifier: Topic :: Multimedia :: Video :: Conversion
Classifier: Topic :: Multimedia :: Sound/Audio
Classifier: Topic :: Multimedia :: Sound/Audio :: Conversion
Requires-Python: >=3.6
Requires-Dist: clint
Requires-Dist: colorama
Requires-Dist: imageio
Requires-Dist: imageio-ffmpeg
Requires-Dist: pytube (>=11.0.2)
Requires-Dist: wheel
